README.md
setup.py
dpyi/__init__.py
dpyi.egg-info/PKG-INFO
dpyi.egg-info/SOURCES.txt
dpyi.egg-info/dependency_links.txt
dpyi.egg-info/requires.txt
dpyi.egg-info/top_level.txt
dpyi/core/__init__.py
dpyi/core/pyi.py
dpyi/core/runtime.py
dpyi/decorators/__init__.py
dpyi/decorators/controller.py
dpyi/decorators/service.py
dpyi/utils/__init__.py
dpyi/utils/response.py