Metadata-Version: 1.0
Name: dpyi
Version: 0.1.1
Summary: django controller and dto service
Home-page: https://github.com/huaqingyi/dpyi
Author: huaqingyi
Author-email: 2304816231@qq.com
License: MIT Licence
Keywords: pip,rest,controller,dpyi,django
Platform: any
